tessipack/MANIFEST.in
tessipack/__init__.py
tessipack/config.py
tessipack/My_catalog/__init__.py
tessipack/My_catalog/my_catalog_v01.csv
tessipack/My_catalog/mycatalog.py
tessipack/My_catalog/__pycache__/__init__.cpython-36.pyc
tessipack/My_catalog/__pycache__/mycatalog.cpython-36.pyc
tessipack/__pycache__/__init__.cpython-36.pyc
tessipack/__pycache__/config.cpython-36.pyc
tessipack/data/data_tessipack/Mycatalog_v1.csv
tessipack/data/data_tessipack/data/extra_flag.flag
tessipack/data/data_tessipack/data/eleanor_aperture/id_gaia/Custom_star_custom_star_s1_ap.txt
tessipack/data/data_tessipack/data/eleanor_aperture/id_gaia/Custom_star_custom_star_s6_ap.txt
tessipack/data/data_tessipack/data/eleanor_aperture/id_gaia/Custom_star_custom_star_s7_ap.txt
tessipack/data/data_tessipack/data/eleanor_aperture/id_gaia/Custom_star_custom_star_s8_ap.txt
tessipack/data/data_tessipack/data/eleanor_aperture/id_gaia/star_TIC_139456051_s1_ap.txt
tessipack/data/data_tessipack/data/eleanor_aperture_current/id_gaia/Custom_star_custom_star_s1_apc.txt
tessipack/data/data_tessipack/data/eleanor_aperture_current/id_gaia/Custom_star_custom_star_s6_apc.txt
tessipack/data/data_tessipack/data/eleanor_aperture_current/id_gaia/Custom_star_custom_star_s7_apc.txt
tessipack/data/data_tessipack/data/eleanor_aperture_current/id_gaia/Custom_star_custom_star_s8_apc.txt
tessipack/data/data_tessipack/data/eleanor_aperture_current/id_gaia/star_TIC_139456051_s1_apc.txt
tessipack/data/data_tessipack/data/eleanor_flux/id_gaia/Custom_star_custom_star_s1_ffi.csv
tessipack/data/data_tessipack/data/eleanor_flux/id_gaia/Custom_star_custom_star_s6_ffi.csv
tessipack/data/data_tessipack/data/eleanor_flux/id_gaia/Custom_star_custom_star_s7_ffi.csv
tessipack/data/data_tessipack/data/eleanor_flux/id_gaia/Custom_star_custom_star_s8_ffi.csv
tessipack/data/data_tessipack/data/eleanor_flux/id_gaia/star_TIC_139456051_s1_ffi.csv
tessipack/data/data_tessipack/data/eleanor_flux_current/id_gaia/Custom_star_custom_star_s1_ffic.csv
tessipack-0.0.21.dist-info/LICENSE
tessipack-0.0.21.dist-info/METADATA
tessipack-0.0.21.dist-info/WHEEL
tessipack-0.0.21.dist-info/top_level.txt
tessipack-0.0.21.dist-info/RECORD
